<?xml version="1.0" encoding="UTF-8"?>

<channel name="displays" version="1.0">
  <property name="Default" type="empty">
    <property name="default" type="string" value="default">
      <property name="Active" type="bool" value="true"/>
      <property name="Resolution" type="string" value="1024x768"/>
      <property name="RefreshRate" type="double" value="61.000000"/>
      <property name="Rotation" type="int" value="0"/>
      <property name="Reflection" type="string" value="0"/>
      <property name="Primary" type="bool" value="false"/>
      <property name="Position" type="empty">
        <property name="X" type="int" value="0"/>
        <property name="Y" type="int" value="0"/>
      </property>
    </property>
    <property name="DisplayPort-1" type="string" value="AUS 28&quot;">
      <property name="Active" type="bool" value="true"/>
      <property name="EDID" type="string" value="0cda5600fe9956ea906e07c9c59891f3de32a655"/>
      <property name="Resolution" type="string" value="3840x2160"/>
      <property name="RefreshRate" type="double" value="59.996625"/>
      <property name="Rotation" type="int" value="0"/>
      <property name="Reflection" type="string" value="0"/>
      <property name="Primary" type="bool" value="false"/>
      <property name="Position" type="empty">
        <property name="X" type="int" value="0"/>
        <property name="Y" type="int" value="0"/>
      </property>
    </property>
  </property>
  <property name="ActiveProfile" type="string" value="Default"/>
</channel>
